<databaseChangeLog xmlns="http://www.liquibase.org/xml/ns/dbchangelog"
                   xmlns:xsi="http://www.w3.org/2001/XMLSchema-instance"
                   xsi:schemaLocation="http://www.liquibase.org/xml/ns/dbchangelog http://www.liquibase.org/xml/ns/dbchangelog/dbchangelog-2.0.xsd">
    
	<changeSet author="amathe" id="FK-1">
		<addForeignKeyConstraint constraintName="FK_TX_INVT_TX_LINE1" baseTableName="TX_INVT_TX_LINE" baseColumnNames="INVTRANSACTION_ID"  referencedTableName="TX_INVT_TX"  referencedColumnNames="ID" />
	</changeSet>	
	<changeSet author="amathe" id="FK-2">
		<addForeignKeyConstraint constraintName="FK_TX_INVT_TX_LINE2" baseTableName="TX_INVT_TX_LINE" baseColumnNames="ITEM_ID"  referencedTableName="MD_PROD"  referencedColumnNames="ID" />
	</changeSet>	
	<changeSet author="amathe" id="FK-3">
		<addForeignKeyConstraint constraintName="FK_TX_INVT_TX_LINE3" baseTableName="TX_INVT_TX_LINE" baseColumnNames="FROM_SUBINV_ID"  referencedTableName="MD_SUBINVT"  referencedColumnNames="ID" />
	</changeSet>	
	<changeSet author="amathe" id="FK-4">
		<addForeignKeyConstraint constraintName="FK_TX_INVT_TX_LINE4" baseTableName="TX_INVT_TX_LINE" baseColumnNames="FROMLOCATOR_ID"  referencedTableName="MD_STOCKLOC"  referencedColumnNames="ID" />
	</changeSet>	
	<changeSet author="amathe" id="FK-5">
		<addForeignKeyConstraint constraintName="FK_TX_INVT_TX_LINE5" baseTableName="TX_INVT_TX_LINE" baseColumnNames="TO_SUBINV_ID"  referencedTableName="MD_SUBINVT"  referencedColumnNames="ID" />
	</changeSet>	
	<changeSet author="amathe" id="FK-6">
		<addForeignKeyConstraint constraintName="FK_TX_INVT_TX_LINE6" baseTableName="TX_INVT_TX_LINE" baseColumnNames="TOLOCATOR_ID"  referencedTableName="MD_STOCKLOC"  referencedColumnNames="ID" />
	</changeSet>	
	<changeSet author="amathe" id="FK-7">
		<addForeignKeyConstraint constraintName="FK_TX_INVT_TX_LINE7" baseTableName="TX_INVT_TX_LINE" baseColumnNames="UOM_ID"  referencedTableName="BD_UOM"  referencedColumnNames="ID" />
	</changeSet>	
</databaseChangeLog>    
